d361/__init__.py
d361/__version__.py
d361/api/__init__.py
d361/api/api_updater.py
d361/api/bulk_operations.py
d361/api/chunked_download.py
d361/api/circuit_breaker.py
d361/api/client.py
d361/api/data_sync.py
d361/api/errors.py
d361/api/generate_models.py
d361/api/metrics.py
d361/api/openapi_integration.py
d361/api/token_manager.py
d361/archive/__init__.py
d361/archive/cache.py
d361/archive/document360_parser.py
d361/archive/parser.py
d361/archive/schema.py
d361/cli/__init__.py
d361/cli/main.py
d361/config/__init__.py
d361/config/environment.py
d361/config/loader.py
d361/config/schema.py
d361/config/secrets.py
d361/config/secrets_manager.py
d361/core/interfaces.py
d361/core/models.py
d361/core/transformers.py
d361/edit/SPEC.md
d361/http/__init__.py
d361/http/client.py
d361/http/compatibility.py
d361/http/middleware.py
d361/mkdocs/__init__.py
d361/mkdocs/exporters/__init__.py
d361/mkdocs/exporters/config_generator.py
d361/mkdocs/exporters/mkdocs_exporter.py
d361/mkdocs/exporters/navigation_builder.py
d361/mkdocs/exporters/theme_optimizer.py
d361/mkdocs/processors/__init__.py
d361/mkdocs/processors/accessibility_optimizer.py
d361/mkdocs/processors/asset_manager.py
d361/mkdocs/processors/content_enhancer.py
d361/mkdocs/processors/cross_reference_resolver.py
d361/mkdocs/processors/markdown_processor.py
d361/mkdocs/processors/plugin_manager.py
d361/mkdocs/processors/seo_optimizer.py
d361/mkdocs/templates/material_theme.yml.j2
d361/mkdocs/templates/mkdocs_base.yml.j2
d361/mkdocs/templates/plugin_configs.yml.j2
d361/offline/__init__.py
d361/offline/__main__.py
d361/offline/browser.py
d361/offline/config.py
d361/offline/content.py
d361/offline/d361_offline.css
d361/offline/d361_offline.py
d361/offline/generator.py
d361/offline/navigation.py
d361/offline/parser.py
d361/plugins/__init__.py
d361/plugins/manager.py
d361/providers/__init__.py
d361/providers/api_provider.py
d361/providers/archive_provider.py
d361/providers/hybrid_provider.py
d361/providers/mock_provider.py
d361-2.2.8.dist-info/METADATA
d361-2.2.8.dist-info/WHEEL
d361-2.2.8.dist-info/entry_points.txt
d361-2.2.8.dist-info/licenses/LICENSE
d361-2.2.8.dist-info/RECORD
