Metadata-Version: 2.4
Name: d361
Version: 2.2.8
Project-URL: Documentation, https://github.com/twardoch/d361#readme
Project-URL: Issues, https://github.com/twardoch/d361/issues
Project-URL: Source, https://github.com/twardoch/d361
Author-email: Adam Twardoch <adam+github@twardoch.com>
License-Expression: MIT
License-File: LICENSE
Classifier: Development Status :: 4 - Beta
Classifier: Programming Language :: Python
Classifier: Programming Language :: Python :: 3.10
Classifier: Programming Language :: Python :: 3.11
Classifier: Programming Language :: Python :: 3.12
Classifier: Programming Language :: Python :: Implementation :: CPython
Classifier: Programming Language :: Python :: Implementation :: PyPy
Requires-Python: >=3.10
Requires-Dist: aiofiles>=23.0.0
Requires-Dist: beautifulsoup4>=4.12.0
Requires-Dist: d361api
Requires-Dist: diskcache>=5.6.0
Requires-Dist: fire>=0.5.0
Requires-Dist: httpx>=0.25.0
Requires-Dist: loguru>=0.7.0
Requires-Dist: lxml>=5.3.1
Requires-Dist: markdownify>=0.11.0
Requires-Dist: playwright>=1.40.0
Requires-Dist: pydantic<3.0,>=2.0
Requires-Dist: rich>=13.0.0
Requires-Dist: tenacity>=8.2.0
Provides-Extra: all
Provides-Extra: api
Requires-Dist: httpx-auth>=0.16.0; extra == 'api'
Provides-Extra: dev
Requires-Dist: bandit>=1.7.0; extra == 'dev'
Requires-Dist: mypy>=1.0.0; extra == 'dev'
Requires-Dist: pre-commit>=3.6.0; extra == 'dev'
Requires-Dist: pyupgrade>=3.19.0; extra == 'dev'
Requires-Dist: ruff>=0.1.0; extra == 'dev'
Requires-Dist: types-aiofiles; extra == 'dev'
Requires-Dist: types-beautifulsoup4; extra == 'dev'
Provides-Extra: monitoring
Requires-Dist: opentelemetry-api>=1.20.0; extra == 'monitoring'
Requires-Dist: opentelemetry-sdk>=1.20.0; extra == 'monitoring'
Requires-Dist: prometheus-client>=0.19.0; extra == 'monitoring'
Provides-Extra: scraping
Requires-Dist: beautifulsoup4>=4.12.0; extra == 'scraping'
Requires-Dist: playwright>=1.40.0; extra == 'scraping'
Provides-Extra: test
Requires-Dist: httpx>=0.25.0; extra == 'test'
Requires-Dist: pytest-asyncio>=0.21.0; extra == 'test'
Requires-Dist: pytest-cov>=4.0.0; extra == 'test'
Requires-Dist: pytest-httpx>=0.21.0; extra == 'test'
Requires-Dist: pytest-mock>=3.10.0; extra == 'test'
Requires-Dist: pytest>=7.0.0; extra == 'test'
